{
  "transactions": [
    {
      "category": "approve",
      "operatorControlled": true,
      "purpose": "Bounded USDC approval for ospex-flow-a: approve-usdc",
      "status": "success",
      "txHash": "0x3fccdf195914eab6df320938fffab6277cc46fae2f1ea1bc2cfda8dfeb8896c9"
    },
    {
      "category": "approve",
      "operatorControlled": true,
      "purpose": "Bounded USDC approval for ospex-flow-a: approve-usdc",
      "status": "success",
      "txHash": "0xa0bf4cc4e07112d1cfb5cc82ae682cfb110bc63eaf9581e12da5a51194754d81"
    },
    {
      "category": "approve",
      "operatorControlled": true,
      "purpose": "Bounded USDC approval for ospex-stage-maker-a: approve-usdc",
      "status": "success",
      "txHash": "0x520ba57619243acaec20851f09d03b91b847cf77f3b1809bf4370f4b9c9f46e8"
    },
    {
      "category": "approve",
      "operatorControlled": true,
      "purpose": "Bounded USDC approval for ospex-stage-maker-a: approve-usdc",
      "status": "success",
      "txHash": "0xa69b09c291504d498be7755c96ac16aaea6d7967d16018571fa2a77148210a3e"
    },
    {
      "category": "approve",
      "operatorControlled": true,
      "purpose": "Bounded USDC approval for ospex-stage-maker-b: approve-usdc",
      "status": "success",
      "txHash": "0x7450693317fde211bf721a401b4a6eaf0af125f6e5967c5a3c12d4d6f3d7d6d8"
    },
    {
      "category": "approve",
      "operatorControlled": true,
      "purpose": "Bounded USDC approval for ospex-stage-maker-b: approve-usdc",
      "status": "success",
      "txHash": "0xd5f4ad3475022dfd02e8589192c173a3d12cecfc2a05c92126d0beb9ee57465e"
    },
    {
      "category": "create-contest",
      "operatorControlled": true,
      "purpose": "Create contest 13 for New York Mets @ Atlanta Braves",
      "status": "success",
      "txHash": "0x85870be65151556be902ba8d38861bb21fdcca407e41b53fe82dda991be156b4"
    },
    {
      "category": "other",
      "operatorControlled": true,
      "purpose": "Request market update for contest 13",
      "status": "success",
      "txHash": "0x703ce2d1a6dbe6e0a80d82064038c11fdfcf6c30a1ced3880361c3c8f316c3c6"
    },
    {
      "category": "seed-match",
      "operatorControlled": true,
      "purpose": "Fully match tiny manual moneyline seed for contest 13 speculation 27",
      "status": "success",
      "txHash": "0x420cc0a5e0efa4cde09486d2ee4e731b3baebe6f65604499fa7acb8b29ef9fc7"
    },
    {
      "category": "seed-match",
      "operatorControlled": true,
      "purpose": "Fully match tiny manual spread seed for contest 13 speculation 28",
      "status": "success",
      "txHash": "0x69a4f94d36d0e1a660b4de3404ece55833b1cb59655a823c6f78e6f78f4295db"
    },
    {
      "category": "seed-match",
      "operatorControlled": true,
      "purpose": "Fully match tiny manual total seed for contest 13 speculation 29",
      "status": "success",
      "txHash": "0x66450153ee202f6b8b6636a9175259eb8ed0eb0b1ed8a76bd12b716a89d825e8"
    },
    {
      "category": "match-commitment",
      "operatorControlled": true,
      "purpose": "Controlled fill against live MM total quote on contest 13",
      "status": "success",
      "txHash": "0x51e2dea37d595ab589be2db96a9707a6875605505b5f3fb26f35db83c46dd112"
    },
    {
      "category": "score-request",
      "operatorControlled": true,
      "purpose": "Request R5 score for contest 13 after MLB official final",
      "status": "success",
      "txHash": "0x9fb26a15fbf3c4c46157261b964b035e49f45c889402d88d2a601eebc4410fd4"
    },
    {
      "category": "score-request",
      "operatorControlled": true,
      "purpose": "Request R5 score for contest 13 after MLB official final",
      "status": "success",
      "txHash": "0xc58564eb53e041f2f1f1b06a6c283dfd825057784c57346b7756f629b9a640a4"
    },
    {
      "category": "settle",
      "operatorControlled": true,
      "purpose": "Settle contest 13 moneyline speculation 27",
      "status": "success",
      "txHash": "0x098a9057c15d8eaa319896fbce83bcfa5a45eacbc6c9d27845b3eba21b37f840"
    },
    {
      "category": "settle",
      "operatorControlled": true,
      "purpose": "Settle contest 13 spread speculation 28",
      "status": "success",
      "txHash": "0xe45cc72e32873278f9ad8b9dfdd5764866a5fdcf18272180b7c446ed184b1fd3"
    },
    {
      "category": "settle",
      "operatorControlled": true,
      "purpose": "Settle contest 13 total speculation 29",
      "status": "success",
      "txHash": "0x3593725e665847f77438583c2f7778636dde5b1048a6ae40f2dd7d88c2156892"
    },
    {
      "category": "claim",
      "operatorControlled": true,
      "purpose": "Claim ospex-stage-maker-a winning position for speculation 27 side upper",
      "status": "success",
      "txHash": "0x76587b336f3bc4c410f06653f479f5afd2c6f30d673fdf0030f92a5d97696966"
    },
    {
      "category": "claim",
      "operatorControlled": true,
      "purpose": "Claim ospex-stage-maker-a winning position for speculation 28 side upper",
      "status": "success",
      "txHash": "0x2fa29cf1c1bfaba58b8db95ec545a1d36e592caccdf27adc0dc0a52fcd752eb5"
    },
    {
      "category": "claim",
      "operatorControlled": true,
      "purpose": "Claim ospex-stage-maker-a winning position for speculation 29 side upper",
      "status": "success",
      "txHash": "0x3d038a02ba863e2e96a9eb35bfcc1e839533a31e2a964218ace1393a1672753e"
    },
    {
      "category": "claim",
      "operatorControlled": true,
      "purpose": "Claim ospex-stage-maker-b winning position for speculation 29 side upper",
      "status": "success",
      "txHash": "0x873b1d649a8973b814db00951a8fd9b9d4ce765d351aea6e97d345c77fe4b7f4"
    }
  ]
}
